{
  "success": true,
  "data": {
    "archived": true,
    "oid": "superloto_archived_20170126",
    "hafta": 484,
    "cekilisTarihi": "26/01/2017",
    "cekilisTuru": "SUPER_LOTO",
    "rakamlar": "06#14#24#36#48#53",
    "rakamlarNumaraSirasi": "06 - 14 - 24 - 36 - 48 - 53",
    "bilenKisiler": [
      {
        "oid": "superloto_20170126_results_3",
        "kisiBasinaDusenIkramiye": 13.95,
        "kisiSayisi": 124354,
        "tur": "$3_BILEN"
      },
      {
        "oid": "superloto_20170126_results_4",
        "kisiBasinaDusenIkramiye": 139,
        "kisiSayisi": 7202,
        "tur": "$4_BILEN"
      },
      {
        "oid": "superloto_20170126_results_5",
        "kisiBasinaDusenIkramiye": 6270.25,
        "kisiSayisi": 149,
        "tur": "$5_BILEN"
      },
      {
        "oid": "superloto_20170126_results_6",
        "kisiBasinaDusenIkramiye": 17373054.9,
        "kisiSayisi": 0,
        "tur": "$6_BILEN"
      }
    ],
    "devretti": true,
    "devirSayisi": null,
    "devirTutari": 0,
    "buyukIkramiye": 17373054.9,
    "buyukIkrKazananIlIlceler": null
  }
}
