{
  "success": true,
  "data": {
    "archived": true,
    "oid": "onnumara_archived_20090608",
    "hafta": 357,
    "cekilisTarihi": "08/06/2009",
    "cekilisTuru": "ON_NUMARA",
    "rakamlar": "02#03#05#09#12#15#21#22#26#30#33#42#44#47#49#54#55#60#64#66#69#74",
    "rakamlarNumaraSirasi": "02 - 03 - 05 - 09 - 12 - 15 - 21 - 22 - 26 - 30 - 33 - 42 - 44 - 47 - 49 - 54 - 55 - 60 - 64 - 66 - 69 - 74",
    "bilenKisiler": [
      {
        "oid": "onnumara_20090608_results_HIC",
        "kisiBasinaDusenIkramiye": 1.4,
        "kisiSayisi": 163114,
        "tur": "$HIC"
      },
      {
        "oid": "onnumara_20090608_results_6",
        "kisiBasinaDusenIkramiye": 1.8,
        "kisiSayisi": 105474,
        "tur": "$6_BILEN"
      },
      {
        "oid": "onnumara_20090608_results_7",
        "kisiBasinaDusenIkramiye": 9.7,
        "kisiSayisi": 17804,
        "tur": "$7_BILEN"
      },
      {
        "oid": "onnumara_20090608_results_8",
        "kisiBasinaDusenIkramiye": 67,
        "kisiSayisi": 1839,
        "tur": "$8_BILEN"
      },
      {
        "oid": "onnumara_20090608_results_9",
        "kisiBasinaDusenIkramiye": 1020.2,
        "kisiSayisi": 120,
        "tur": "$9_BILEN"
      },
      {
        "oid": "onnumara_20090608_results_10",
        "kisiBasinaDusenIkramiye": 183633.45,
        "kisiSayisi": 1,
        "tur": "$10_BILEN"
      }
    ],
    "devretti": false,
    "devirSayisi": null,
    "devirTutari": 0,
    "buyukIkramiye": 183633.45,
    "buyukIkrKazananIlIlceler": null
  }
}
