{
  "success": true,
  "data": {
    "archived": true,
    "oid": "onnumara_archived_20100104",
    "hafta": 387,
    "cekilisTarihi": "04/01/2010",
    "cekilisTuru": "ON_NUMARA",
    "rakamlar": "01#02#10#17#21#27#28#29#31#43#49#51#54#55#58#60#62#64#69#72#77#79",
    "rakamlarNumaraSirasi": "01 - 02 - 10 - 17 - 21 - 27 - 28 - 29 - 31 - 43 - 49 - 51 - 54 - 55 - 58 - 60 - 62 - 64 - 69 - 72 - 77 - 79",
    "bilenKisiler": [
      {
        "oid": "onnumara_20100104_results_HIC",
        "kisiBasinaDusenIkramiye": 1.35,
        "kisiSayisi": 201891,
        "tur": "$HIC"
      },
      {
        "oid": "onnumara_20100104_results_6",
        "kisiBasinaDusenIkramiye": 2,
        "kisiSayisi": 107634,
        "tur": "$6_BILEN"
      },
      {
        "oid": "onnumara_20100104_results_7",
        "kisiBasinaDusenIkramiye": 11.8,
        "kisiSayisi": 17155,
        "tur": "$7_BILEN"
      },
      {
        "oid": "onnumara_20100104_results_8",
        "kisiBasinaDusenIkramiye": 89.85,
        "kisiSayisi": 1596,
        "tur": "$8_BILEN"
      },
      {
        "oid": "onnumara_20100104_results_9",
        "kisiBasinaDusenIkramiye": 1832.65,
        "kisiSayisi": 78,
        "tur": "$9_BILEN"
      },
      {
        "oid": "onnumara_20100104_results_10",
        "kisiBasinaDusenIkramiye": 107189.55,
        "kisiSayisi": 2,
        "tur": "$10_BILEN"
      }
    ],
    "devretti": false,
    "devirSayisi": null,
    "devirTutari": 0,
    "buyukIkramiye": 214379.1,
    "buyukIkrKazananIlIlceler": null
  }
}
