{
  "success": true,
  "data": {
    "archived": true,
    "oid": "onnumara_archived_20161205",
    "hafta": 748,
    "cekilisTarihi": "05/12/2016",
    "cekilisTuru": "ON_NUMARA",
    "rakamlar": "06#07#11#15#17#19#23#24#29#31#32#34#40#43#51#54#59#61#66#73#76#77",
    "rakamlarNumaraSirasi": "06 - 07 - 11 - 15 - 17 - 19 - 23 - 24 - 29 - 31 - 32 - 34 - 40 - 43 - 51 - 54 - 59 - 61 - 66 - 73 - 76 - 77",
    "bilenKisiler": [
      {
        "oid": "onnumara_20161205_results_HIC",
        "kisiBasinaDusenIkramiye": 3.15,
        "kisiSayisi": 152868,
        "tur": "$HIC"
      },
      {
        "oid": "onnumara_20161205_results_6",
        "kisiBasinaDusenIkramiye": 4.05,
        "kisiSayisi": 93142,
        "tur": "$6_BILEN"
      },
      {
        "oid": "onnumara_20161205_results_7",
        "kisiBasinaDusenIkramiye": 23.45,
        "kisiSayisi": 15239,
        "tur": "$7_BILEN"
      },
      {
        "oid": "onnumara_20161205_results_8",
        "kisiBasinaDusenIkramiye": 128.95,
        "kisiSayisi": 1457,
        "tur": "$8_BILEN"
      },
      {
        "oid": "onnumara_20161205_results_9",
        "kisiBasinaDusenIkramiye": 2713.85,
        "kisiSayisi": 69,
        "tur": "$9_BILEN"
      },
      {
        "oid": "onnumara_20161205_results_10",
        "kisiBasinaDusenIkramiye": 280812.85,
        "kisiSayisi": 1,
        "tur": "$10_BILEN"
      }
    ],
    "devretti": false,
    "devirSayisi": null,
    "devirTutari": 0,
    "buyukIkramiye": 280812.85,
    "buyukIkrKazananIlIlceler": null
  }
}
