{
  "success": true,
  "data": {
    "archived": true,
    "oid": "sayisal_archived_19971101",
    "hafta": 51,
    "cekilisTarihi": "01/11/1997",
    "cekilisTuru": "SAYISAL_LOTO",
    "rakamlar": "01#13#16#19#33#35",
    "rakamlarNumaraSirasi": "01 - 13 - 16 - 19 - 33 - 35",
    "bilenKisiler": [
      {
        "oid": "sayisal_19971101_results_3",
        "kisiBasinaDusenIkramiye": 0.43,
        "kisiSayisi": 291352,
        "tur": "$3_BILEN"
      },
      {
        "oid": "sayisal_19971101_results_4",
        "kisiBasinaDusenIkramiye": 4.34,
        "kisiSayisi": 14479,
        "tur": "$4_BILEN"
      },
      {
        "oid": "sayisal_19971101_results_5",
        "kisiBasinaDusenIkramiye": 568.23,
        "kisiSayisi": 219,
        "tur": "$5_BILEN"
      },
      {
        "oid": "sayisal_19971101_results_6",
        "kisiBasinaDusenIkramiye": 133301.1,
        "kisiSayisi": 0,
        "tur": "$6_BILEN"
      }
    ],
    "devretti": true,
    "devirSayisi": null,
    "devirTutari": 0,
    "buyukIkramiye": 133301.1,
    "buyukIkrKazananIlIlceler": null
  }
}
