{
  "success": true,
  "data": {
    "archived": true,
    "oid": "sayisal_archived_20041113",
    "hafta": 418,
    "cekilisTarihi": "13/11/2004",
    "cekilisTuru": "SAYISAL_LOTO",
    "rakamlar": "17#29#31#35#39#46",
    "rakamlarNumaraSirasi": "17 - 29 - 31 - 35 - 39 - 46",
    "bilenKisiler": [
      {
        "oid": "sayisal_20041113_results_3",
        "kisiBasinaDusenIkramiye": 1.9,
        "kisiSayisi": 441556,
        "tur": "$3_BILEN"
      },
      {
        "oid": "sayisal_20041113_results_4",
        "kisiBasinaDusenIkramiye": 13.9,
        "kisiSayisi": 23131,
        "tur": "$4_BILEN"
      },
      {
        "oid": "sayisal_20041113_results_5",
        "kisiBasinaDusenIkramiye": 1834.8,
        "kisiSayisi": 367,
        "tur": "$5_BILEN"
      },
      {
        "oid": "sayisal_20041113_results_6",
        "kisiBasinaDusenIkramiye": 611297.5,
        "kisiSayisi": 2,
        "tur": "$6_BILEN"
      }
    ],
    "devretti": false,
    "devirSayisi": null,
    "devirTutari": 0,
    "buyukIkramiye": 1222595,
    "buyukIkrKazananIlIlceler": null
  }
}
