{
  "success": true,
  "data": {
    "archived": true,
    "oid": "sayisal_archived_20120121",
    "hafta": 793,
    "cekilisTarihi": "21/01/2012",
    "cekilisTuru": "SAYISAL_LOTO",
    "rakamlar": "07#10#17#20#28#36",
    "rakamlarNumaraSirasi": "07 - 10 - 17 - 20 - 28 - 36",
    "bilenKisiler": [
      {
        "oid": "sayisal_20120121_results_3",
        "kisiBasinaDusenIkramiye": 5.5,
        "kisiSayisi": 239092,
        "tur": "$3_BILEN"
      },
      {
        "oid": "sayisal_20120121_results_4",
        "kisiBasinaDusenIkramiye": 35.9,
        "kisiSayisi": 13216,
        "tur": "$4_BILEN"
      },
      {
        "oid": "sayisal_20120121_results_5",
        "kisiBasinaDusenIkramiye": 2481.45,
        "kisiSayisi": 251,
        "tur": "$5_BILEN"
      },
      {
        "oid": "sayisal_20120121_results_6",
        "kisiBasinaDusenIkramiye": 1478523,
        "kisiSayisi": 1,
        "tur": "$6_BILEN"
      }
    ],
    "devretti": false,
    "devirSayisi": null,
    "devirTutari": 0,
    "buyukIkramiye": 1478523,
    "buyukIkrKazananIlIlceler": null
  }
}
