{
  "success": true,
  "data": {
    "archived": true,
    "oid": "onnumara_archived_20120903",
    "hafta": 526,
    "cekilisTarihi": "03/09/2012",
    "cekilisTuru": "ON_NUMARA",
    "rakamlar": "05#06#16#18#20#26#27#28#35#39#42#45#48#50#53#58#60#67#72#75#76#78",
    "rakamlarNumaraSirasi": "05 - 06 - 16 - 18 - 20 - 26 - 27 - 28 - 35 - 39 - 42 - 45 - 48 - 50 - 53 - 58 - 60 - 67 - 72 - 75 - 76 - 78",
    "bilenKisiler": [
      {
        "oid": "onnumara_20120903_results_HIC",
        "kisiBasinaDusenIkramiye": 2.3,
        "kisiSayisi": 153274,
        "tur": "$HIC"
      },
      {
        "oid": "onnumara_20120903_results_6",
        "kisiBasinaDusenIkramiye": 3.1,
        "kisiSayisi": 90707,
        "tur": "$6_BILEN"
      },
      {
        "oid": "onnumara_20120903_results_7",
        "kisiBasinaDusenIkramiye": 17.8,
        "kisiSayisi": 14714,
        "tur": "$7_BILEN"
      },
      {
        "oid": "onnumara_20120903_results_8",
        "kisiBasinaDusenIkramiye": 94.5,
        "kisiSayisi": 1461,
        "tur": "$8_BILEN"
      },
      {
        "oid": "onnumara_20120903_results_9",
        "kisiBasinaDusenIkramiye": 1914.95,
        "kisiSayisi": 72,
        "tur": "$9_BILEN"
      },
      {
        "oid": "onnumara_20120903_results_10",
        "kisiBasinaDusenIkramiye": 41350.2,
        "kisiSayisi": 5,
        "tur": "$10_BILEN"
      }
    ],
    "devretti": false,
    "devirSayisi": null,
    "devirTutari": 0,
    "buyukIkramiye": 206751,
    "buyukIkrKazananIlIlceler": null
  }
}
