{"archived":true,"oid":"onnumara_archived_20121224","hafta":542,"cekilisTarihi":"24/12/2012","cekilisTuru":"ON_NUMARA","rakamlar":"03#05#09#13#14#16#20#23#25#30#31#33#44#49#56#57#59#63#65#70#76#78","rakamlarNumaraSirasi":"03 - 05 - 09 - 13 - 14 - 16 - 20 - 23 - 25 - 30 - 31 - 33 - 44 - 49 - 56 - 57 - 59 - 63 - 65 - 70 - 76 - 78","bilenKisiler":[{"oid":"onnumara_20121224_results_HIC","kisiBasinaDusenIkramiye":2.15,"kisiSayisi":201812,"tur":"$HIC"},{"oid":"onnumara_20121224_results_6","kisiBasinaDusenIkramiye":3.15,"kisiSayisi":105894,"tur":"$6_BILEN"},{"oid":"onnumara_20121224_results_7","kisiBasinaDusenIkramiye":19.1,"kisiSayisi":16607,"tur":"$7_BILEN"},{"oid":"onnumara_20121224_results_8","kisiBasinaDusenIkramiye":106.5,"kisiSayisi":1570,"tur":"$8_BILEN"},{"oid":"onnumara_20121224_results_9","kisiBasinaDusenIkramiye":2061.7,"kisiSayisi":81,"tur":"$9_BILEN"},{"oid":"onnumara_20121224_results_10","kisiBasinaDusenIkramiye":50078.05,"kisiSayisi":5,"tur":"$10_BILEN"}],"devretti":false,"devirSayisi":null,"devirTutari":0,"buyukIkramiye":250390.25,"buyukIkrKazananIlIlceler":null}