{"archived":true,"oid":"sanstopu_archived_20050810","hafta":217,"cekilisTarihi":"10/08/2005","cekilisTuru":"SANS_TOPU","rakamlar":"04#15#22#26#34#07","rakamlarNumaraSirasi":"04 - 15 - 22 - 26 - 34 - 07","bilenKisiler":[{"oid":"sanstopu_20050810_results_1_1","kisiBasinaDusenIkramiye":1.4,"kisiSayisi":258270,"tur":"$1_1_BILEN"},{"oid":"sanstopu_20050810_results_2_1","kisiBasinaDusenIkramiye":2.95,"kisiSayisi":76450,"tur":"$2_1_BILEN"},{"oid":"sanstopu_20050810_results_3","kisiBasinaDusenIkramiye":2.3,"kisiSayisi":96292,"tur":"$3_BILEN"},{"oid":"sanstopu_20050810_results_3_1","kisiBasinaDusenIkramiye":9.75,"kisiSayisi":7835,"tur":"$3_1_BILEN"},{"oid":"sanstopu_20050810_results_4","kisiBasinaDusenIkramiye":18.1,"kisiSayisi":3257,"tur":"$4_BILEN"},{"oid":"sanstopu_20050810_results_4_1","kisiBasinaDusenIkramiye":224.65,"kisiSayisi":263,"tur":"$4_1_BILEN"},{"oid":"sanstopu_20050810_results_5","kisiBasinaDusenIkramiye":1924.05,"kisiSayisi":23,"tur":"$5_BILEN"},{"oid":"sanstopu_20050810_results_5_1","kisiBasinaDusenIkramiye":427753.62,"kisiSayisi":0,"tur":"$5_1_BILEN"}],"devretti":true,"devirSayisi":null,"devirTutari":0,"buyukIkramiye":427753.62,"buyukIkrKazananIlIlceler":null}