{"archived":true,"oid":"sanstopu_archived_20101110","hafta":491,"cekilisTarihi":"10/11/2010","cekilisTuru":"SANS_TOPU","rakamlar":"01#09#12#20#30#14","rakamlarNumaraSirasi":"01 - 09 - 12 - 20 - 30 - 14","bilenKisiler":[{"oid":"sanstopu_20101110_results_1_1","kisiBasinaDusenIkramiye":1.7,"kisiSayisi":234204,"tur":"$1_1_BILEN"},{"oid":"sanstopu_20101110_results_2_1","kisiBasinaDusenIkramiye":3.4,"kisiSayisi":70174,"tur":"$2_1_BILEN"},{"oid":"sanstopu_20101110_results_3","kisiBasinaDusenIkramiye":2.1,"kisiSayisi":110585,"tur":"$3_BILEN"},{"oid":"sanstopu_20101110_results_3_1","kisiBasinaDusenIkramiye":11.6,"kisiSayisi":7514,"tur":"$3_1_BILEN"},{"oid":"sanstopu_20101110_results_4","kisiBasinaDusenIkramiye":17.5,"kisiSayisi":3825,"tur":"$4_BILEN"},{"oid":"sanstopu_20101110_results_4_1","kisiBasinaDusenIkramiye":180.95,"kisiSayisi":279,"tur":"$4_1_BILEN"},{"oid":"sanstopu_20101110_results_5","kisiBasinaDusenIkramiye":1677.6,"kisiSayisi":30,"tur":"$5_BILEN"},{"oid":"sanstopu_20101110_results_5_1","kisiBasinaDusenIkramiye":553554.45,"kisiSayisi":1,"tur":"$5_1_BILEN"}],"devretti":false,"devirSayisi":null,"devirTutari":0,"buyukIkramiye":553554.45,"buyukIkrKazananIlIlceler":null}