{
  "success": true,
  "data": {
    "archived": true,
    "oid": "sayisal_archived_20000422",
    "hafta": 180,
    "cekilisTarihi": "22/04/2000",
    "cekilisTuru": "SAYISAL_LOTO",
    "rakamlar": "02#17#20#29#30#35",
    "rakamlarNumaraSirasi": "02 - 17 - 20 - 29 - 30 - 35",
    "bilenKisiler": [
      {
        "oid": "sayisal_20000422_results_3",
        "kisiBasinaDusenIkramiye": 0.75,
        "kisiSayisi": 666360,
        "tur": "$3_BILEN"
      },
      {
        "oid": "sayisal_20000422_results_4",
        "kisiBasinaDusenIkramiye": 7.01,
        "kisiSayisi": 35506,
        "tur": "$4_BILEN"
      },
      {
        "oid": "sayisal_20000422_results_5",
        "kisiBasinaDusenIkramiye": 819.95,
        "kisiSayisi": 606,
        "tur": "$5_BILEN"
      },
      {
        "oid": "sayisal_20000422_results_6",
        "kisiBasinaDusenIkramiye": 231343.44,
        "kisiSayisi": 4,
        "tur": "$6_BILEN"
      }
    ],
    "devretti": false,
    "devirSayisi": null,
    "devirTutari": 0,
    "buyukIkramiye": 925373.76,
    "buyukIkrKazananIlIlceler": null
  }
}
