{
  "success": true,
  "data": {
    "archived": true,
    "oid": "sanstopu_archived_20080813",
    "hafta": 374,
    "cekilisTarihi": "13/08/2008",
    "cekilisTuru": "SANS_TOPU",
    "rakamlar": "05#06#10#17#20#01",
    "rakamlarNumaraSirasi": "05 - 06 - 10 - 17 - 20 - 01",
    "bilenKisiler": [
      {
        "oid": "sanstopu_20080813_results_1_1",
        "kisiBasinaDusenIkramiye": 1.75,
        "kisiSayisi": 232206,
        "tur": "$1_1_BILEN"
      },
      {
        "oid": "sanstopu_20080813_results_2_1",
        "kisiBasinaDusenIkramiye": 3.15,
        "kisiSayisi": 75259,
        "tur": "$2_1_BILEN"
      },
      {
        "oid": "sanstopu_20080813_results_3",
        "kisiBasinaDusenIkramiye": 1.65,
        "kisiSayisi": 143275,
        "tur": "$3_BILEN"
      },
      {
        "oid": "sanstopu_20080813_results_3_1",
        "kisiBasinaDusenIkramiye": 10.4,
        "kisiSayisi": 8711,
        "tur": "$3_1_BILEN"
      },
      {
        "oid": "sanstopu_20080813_results_4",
        "kisiBasinaDusenIkramiye": 13.5,
        "kisiSayisi": 5040,
        "tur": "$4_BILEN"
      },
      {
        "oid": "sanstopu_20080813_results_4_1",
        "kisiBasinaDusenIkramiye": 165.55,
        "kisiSayisi": 309,
        "tur": "$4_1_BILEN"
      },
      {
        "oid": "sanstopu_20080813_results_5",
        "kisiBasinaDusenIkramiye": 1824.5,
        "kisiSayisi": 28,
        "tur": "$5_BILEN"
      },
      {
        "oid": "sanstopu_20080813_results_5_1",
        "kisiBasinaDusenIkramiye": 561840.05,
        "kisiSayisi": 1,
        "tur": "$5_1_BILEN"
      }
    ],
    "devretti": false,
    "devirSayisi": null,
    "devirTutari": 0,
    "buyukIkramiye": 561840.05,
    "buyukIkrKazananIlIlceler": null
  }
}
