{
  "success": true,
  "data": {
    "archived": true,
    "oid": "sanstopu_archived_20141224",
    "hafta": 706,
    "cekilisTarihi": "24/12/2014",
    "cekilisTuru": "SANS_TOPU",
    "rakamlar": "03#12#15#22#27#13",
    "rakamlarNumaraSirasi": "03 - 12 - 15 - 22 - 27 - 13",
    "bilenKisiler": [
      {
        "oid": "sanstopu_20141224_results_1_1",
        "kisiBasinaDusenIkramiye": 3.8,
        "kisiSayisi": 170877,
        "tur": "$1_1_BILEN"
      },
      {
        "oid": "sanstopu_20141224_results_2_1",
        "kisiBasinaDusenIkramiye": 6.7,
        "kisiSayisi": 51539,
        "tur": "$2_1_BILEN"
      },
      {
        "oid": "sanstopu_20141224_results_3",
        "kisiBasinaDusenIkramiye": 4,
        "kisiSayisi": 85126,
        "tur": "$3_BILEN"
      },
      {
        "oid": "sanstopu_20141224_results_3_1",
        "kisiBasinaDusenIkramiye": 22.2,
        "kisiSayisi": 5495,
        "tur": "$3_1_BILEN"
      },
      {
        "oid": "sanstopu_20141224_results_4",
        "kisiBasinaDusenIkramiye": 30.5,
        "kisiSayisi": 3189,
        "tur": "$4_BILEN"
      },
      {
        "oid": "sanstopu_20141224_results_4_1",
        "kisiBasinaDusenIkramiye": 330.15,
        "kisiSayisi": 221,
        "tur": "$4_1_BILEN"
      },
      {
        "oid": "sanstopu_20141224_results_5",
        "kisiBasinaDusenIkramiye": 3312.4,
        "kisiSayisi": 22,
        "tur": "$5_BILEN"
      },
      {
        "oid": "sanstopu_20141224_results_5_1",
        "kisiBasinaDusenIkramiye": 1399875.05,
        "kisiSayisi": 1,
        "tur": "$5_1_BILEN"
      }
    ],
    "devretti": false,
    "devirSayisi": null,
    "devirTutari": 0,
    "buyukIkramiye": 1399875.05,
    "buyukIkrKazananIlIlceler": null
  }
}
