{"archived":true,"oid":"sanstopu_archived_20051228","hafta":237,"cekilisTarihi":"28/12/2005","cekilisTuru":"SANS_TOPU","rakamlar":"04#17#26#27#31#08","rakamlarNumaraSirasi":"04 - 17 - 26 - 27 - 31 - 08","bilenKisiler":[{"oid":"sanstopu_20051228_results_1_1","kisiBasinaDusenIkramiye":1.45,"kisiSayisi":315622,"tur":"$1_1_BILEN"},{"oid":"sanstopu_20051228_results_2_1","kisiBasinaDusenIkramiye":2.9,"kisiSayisi":98376,"tur":"$2_1_BILEN"},{"oid":"sanstopu_20051228_results_3","kisiBasinaDusenIkramiye":1.9,"kisiSayisi":145177,"tur":"$3_BILEN"},{"oid":"sanstopu_20051228_results_3_1","kisiBasinaDusenIkramiye":8.85,"kisiSayisi":11167,"tur":"$3_1_BILEN"},{"oid":"sanstopu_20051228_results_4","kisiBasinaDusenIkramiye":12.45,"kisiSayisi":5977,"tur":"$4_BILEN"},{"oid":"sanstopu_20051228_results_4_1","kisiBasinaDusenIkramiye":177.45,"kisiSayisi":421,"tur":"$4_1_BILEN"},{"oid":"sanstopu_20051228_results_5","kisiBasinaDusenIkramiye":1995.85,"kisiSayisi":28,"tur":"$5_BILEN"},{"oid":"sanstopu_20051228_results_5_1","kisiBasinaDusenIkramiye":993865.2,"kisiSayisi":1,"tur":"$5_1_BILEN"}],"devretti":false,"devirSayisi":null,"devirTutari":0,"buyukIkramiye":993865.2,"buyukIkrKazananIlIlceler":null}