{
  "success": true,
  "data": {
    "archived": true,
    "oid": "sanstopu_archived_20170712",
    "hafta": 839,
    "cekilisTarihi": "12/07/2017",
    "cekilisTuru": "SANS_TOPU",
    "rakamlar": "06#08#10#26#27#11",
    "rakamlarNumaraSirasi": "06 - 08 - 10 - 26 - 27 - 11",
    "bilenKisiler": [
      {
        "oid": "sanstopu_20170712_results_1_1",
        "kisiBasinaDusenIkramiye": 3.25,
        "kisiSayisi": 205364,
        "tur": "$1_1_BILEN"
      },
      {
        "oid": "sanstopu_20170712_results_2_1",
        "kisiBasinaDusenIkramiye": 5.7,
        "kisiSayisi": 62023,
        "tur": "$2_1_BILEN"
      },
      {
        "oid": "sanstopu_20170712_results_3",
        "kisiBasinaDusenIkramiye": 4.15,
        "kisiSayisi": 84492,
        "tur": "$3_BILEN"
      },
      {
        "oid": "sanstopu_20170712_results_3_1",
        "kisiBasinaDusenIkramiye": 19.35,
        "kisiSayisi": 6508,
        "tur": "$3_1_BILEN"
      },
      {
        "oid": "sanstopu_20170712_results_4",
        "kisiBasinaDusenIkramiye": 37.3,
        "kisiSayisi": 2677,
        "tur": "$4_BILEN"
      },
      {
        "oid": "sanstopu_20170712_results_4_1",
        "kisiBasinaDusenIkramiye": 353.8,
        "kisiSayisi": 212,
        "tur": "$4_1_BILEN"
      },
      {
        "oid": "sanstopu_20170712_results_5",
        "kisiBasinaDusenIkramiye": 3255.95,
        "kisiSayisi": 23,
        "tur": "$5_BILEN"
      },
      {
        "oid": "sanstopu_20170712_results_5_1",
        "kisiBasinaDusenIkramiye": 712272.2,
        "kisiSayisi": 2,
        "tur": "$5_1_BILEN"
      }
    ],
    "devretti": false,
    "devirSayisi": null,
    "devirTutari": 0,
    "buyukIkramiye": 1424544.4,
    "buyukIkrKazananIlIlceler": null
  }
}
