{"oid":"3zh7csk2f0lx6m00","hafta":628,"buyukIkramiyeKazananIl":"","cekilisTarihi":"31/10/2019","cekilisTuru":"SUPER_LOTO","rakamlar":"24#06#46#28#22#34","rakamlarNumaraSirasi":"06 - 22 - 24 - 28 - 34 - 46","devretti":true,"devirSayisi":2,"bilenKisiler":[{"oid":"3zi2z7k2f0lx6h03","kisiBasinaDusenIkramiye":13.9,"kisiSayisi":72726,"tur":"$3_BILEN"},{"oid":"3zi2z7k2f0lx6h02","kisiBasinaDusenIkramiye":157.8,"kisiSayisi":3808,"tur":"$4_BILEN"},{"oid":"3zi2z7k2f0lx6h01","kisiBasinaDusenIkramiye":7177.2,"kisiSayisi":77,"tur":"$5_BILEN"},{"oid":"3zi2z7k2f0lx6h00","kisiBasinaDusenIkramiye":4673977.48,"kisiSayisi":0,"tur":"$6_BILEN"}],"buyukIkrKazananIlIlceler":[],"kibrisHasilati":50320,"devirTutari":2233224.48,"kolonSayisi":5027069,"kdv":1526006.14,"toplamHasilat":10054138,"hasilat":8528131.86,"sov":852813.19,"ikramiyeEH":7675318.67,"buyukIkramiye":2440751.34,"haftayaDevredenTutar":4673977.48}