{
  "success": true,
  "data": {
    "archived": true,
    "oid": "superloto_archived_20140123",
    "hafta": 327,
    "cekilisTarihi": "23/01/2014",
    "cekilisTuru": "SUPER_LOTO",
    "rakamlar": "02#06#13#24#39#41",
    "rakamlarNumaraSirasi": "02 - 06 - 13 - 24 - 39 - 41",
    "bilenKisiler": [
      {
        "oid": "superloto_20140123_results_3",
        "kisiBasinaDusenIkramiye": 7.55,
        "kisiSayisi": 89778,
        "tur": "$3_BILEN"
      },
      {
        "oid": "superloto_20140123_results_4",
        "kisiBasinaDusenIkramiye": 91.5,
        "kisiSayisi": 4332,
        "tur": "$4_BILEN"
      },
      {
        "oid": "superloto_20140123_results_5",
        "kisiBasinaDusenIkramiye": 5240.85,
        "kisiSayisi": 70,
        "tur": "$5_BILEN"
      },
      {
        "oid": "superloto_20140123_results_6",
        "kisiBasinaDusenIkramiye": 1179056.56,
        "kisiSayisi": 0,
        "tur": "$6_BILEN"
      }
    ],
    "devretti": true,
    "devirSayisi": null,
    "devirTutari": 0,
    "buyukIkramiye": 1179056.56,
    "buyukIkrKazananIlIlceler": null
  }
}
