{"archived":true,"oid":"sayisal_archived_20000624","hafta":189,"cekilisTarihi":"24/06/2000","cekilisTuru":"SAYISAL_LOTO","rakamlar":"04#06#11#16#21#23","rakamlarNumaraSirasi":"04 - 06 - 11 - 16 - 21 - 23","bilenKisiler":[{"oid":"sayisal_20000624_results_3","kisiBasinaDusenIkramiye":0.6,"kisiSayisi":822162,"tur":"$3_BILEN"},{"oid":"sayisal_20000624_results_4","kisiBasinaDusenIkramiye":4.93,"kisiSayisi":50620,"tur":"$4_BILEN"},{"oid":"sayisal_20000624_results_5","kisiBasinaDusenIkramiye":445.17,"kisiSayisi":1113,"tur":"$5_BILEN"},{"oid":"sayisal_20000624_results_6","kisiBasinaDusenIkramiye":158897.12,"kisiSayisi":6,"tur":"$6_BILEN"}],"devretti":false,"devirSayisi":null,"devirTutari":0,"buyukIkramiye":953382.72,"buyukIkrKazananIlIlceler":null}