{"archived":true,"oid":"sayisal_archived_20110115","hafta":740,"cekilisTarihi":"15/01/2011","cekilisTuru":"SAYISAL_LOTO","rakamlar":"01#09#17#28#34#37","rakamlarNumaraSirasi":"01 - 09 - 17 - 28 - 34 - 37","bilenKisiler":[{"oid":"sayisal_20110115_results_3","kisiBasinaDusenIkramiye":4.2,"kisiSayisi":326611,"tur":"$3_BILEN"},{"oid":"sayisal_20110115_results_4","kisiBasinaDusenIkramiye":25.15,"kisiSayisi":17172,"tur":"$4_BILEN"},{"oid":"sayisal_20110115_results_5","kisiBasinaDusenIkramiye":2294.5,"kisiSayisi":337,"tur":"$5_BILEN"},{"oid":"sayisal_20110115_results_6","kisiBasinaDusenIkramiye":3350415.6,"kisiSayisi":1,"tur":"$6_BILEN"}],"devretti":false,"devirSayisi":null,"devirTutari":0,"buyukIkramiye":3350415.6,"buyukIkrKazananIlIlceler":null}