{
  "success": true,
  "data": {
    "cekilisAdi": "19/01/2019 BİLET KONTROL ŞUBE MÜDÜRLÜĞÜ",
    "cekilisTarihi": "19/01/2019",
    "haneSayisi": 6,
    "sonuclar": [
      {
        "haneSayisi": 6,
        "tip": "$6_RAKAM",
        "ikramiye": 4000000,
        "numaralar": ["431211"]
      },
      {
        "haneSayisi": 6,
        "tip": "$6_RAKAM",
        "ikramiye": 400000,
        "numaralar": ["816823"]
      },
      {
        "haneSayisi": 6,
        "tip": "$6_RAKAM",
        "ikramiye": 40000,
        "numaralar": ["699987", "949919", "935361"]
      },
      {
        "haneSayisi": 6,
        "tip": "$6_RAKAM",
        "ikramiye": 10000,
        "numaralar": [
          "711212",
          "002679",
          "261355",
          "183240",
          "443319",
          "090128",
          "840886",
          "367579",
          "719094",
          "546988"
        ]
      },
      {
        "haneSayisi": 6,
        "tip": "$6_RAKAM",
        "ikramiye": 5000,
        "numaralar": [
          "081359",
          "846761",
          "878644",
          "650912",
          "254003",
          "612825",
          "094385",
          "002962",
          "784438",
          "942673"
        ]
      },
      {
        "haneSayisi": 6,
        "tip": "$6_RAKAM",
        "ikramiye": 1000,
        "numaralar": [
          "529964",
          "941450",
          "126305",
          "297363",
          "007499",
          "782642",
          "908087",
          "806052",
          "180544",
          "835268",
          "844417",
          "746771",
          "329647",
          "945453",
          "861457",
          "850502",
          "520335",
          "690873",
          "555784",
          "759031",
          "998378",
          "967304",
          "852635",
          "205715",
          "392915",
          "913754",
          "857963",
          "317045",
          "374694",
          "656896",
          "061501",
          "814322",
          "559647",
          "578226",
          "097010",
          "596563",
          "953396",
          "492195",
          "239367",
          "207911",
          "950860",
          "797817",
          "015310",
          "728283",
          "308411",
          "689138",
          "200372",
          "550410",
          "500897",
          "946737",
          "389579",
          "281698",
          "246914",
          "035902",
          "799611",
          "596865",
          "878322",
          "494704",
          "730597",
          "990169",
          "184215",
          "455593",
          "168161",
          "907631",
          "939246",
          "064906",
          "340312",
          "545059",
          "113338",
          "029414",
          "972886",
          "599467",
          "539314",
          "865456",
          "070014",
          "105305",
          "467710",
          "048563",
          "053560",
          "063728",
          "450304",
          "608058",
          "119060",
          "238905",
          "743680",
          "398050",
          "777652",
          "838623",
          "904462",
          "533848",
          "106565",
          "593454",
          "887689",
          "362813",
          "281573",
          "193977",
          "033289",
          "675640",
          "473819",
          "930254",
          "585216",
          "942496",
          "496369",
          "236017",
          "101425",
          "681746",
          "908605",
          "986682",
          "231095",
          "179961",
          "841211",
          "947824",
          "642861",
          "586435",
          "056068",
          "548852",
          "316416",
          "456929",
          "861178",
          "503263",
          "482105",
          "456828",
          "736678",
          "563192",
          "965831",
          "189529",
          "465446",
          "602883",
          "626623",
          "600693",
          "249633",
          "509216",
          "183576",
          "081065",
          "183175",
          "155741",
          "017815",
          "586122",
          "417283",
          "050971",
          "437585",
          "266098",
          "316598",
          "014316",
          "879894",
          "977629",
          "436641",
          "232174",
          "460204",
          "749761"
        ]
      },
      {
        "haneSayisi": 5,
        "tip": "SON_BES_RAKAM",
        "ikramiye": 400,
        "numaralar": [
          "03467",
          "39134",
          "58052",
          "25816",
          "06557",
          "76106",
          "31936",
          "07635",
          "58574",
          "42282",
          "24065",
          "99593",
          "45536",
          "42996",
          "92507",
          "45267",
          "87575",
          "81675",
          "01211",
          "08830",
          "52019",
          "25976",
          "60543",
          "01096",
          "35992",
          "86717",
          "92388",
          "89730",
          "24326",
          "36651",
          "16330",
          "99911",
          "43398",
          "19958",
          "05932",
          "68356",
          "46136",
          "21188",
          "54824",
          "46832",
          "96833",
          "63244",
          "28191",
          "42080",
          "96324",
          "56700",
          "19162",
          "67973",
          "86512",
          "93660"
        ]
      },
      {
        "haneSayisi": 4,
        "tip": "SON_DORT_RAKAM",
        "ikramiye": 300,
        "numaralar": [
          "8963",
          "5912",
          "7859",
          "8983",
          "4879",
          "3150",
          "9075",
          "1157",
          "5726",
          "7471",
          "0096",
          "8413",
          "6388",
          "3665",
          "2814",
          "2470",
          "4204",
          "3590",
          "4218",
          "0735"
        ]
      },
      {
        "haneSayisi": 3,
        "tip": "SON_UC_RAKAM",
        "ikramiye": 160,
        "numaralar": [
          "068",
          "336",
          "543",
          "328",
          "312",
          "814",
          "404",
          "400",
          "695",
          "751",
          "245",
          "341"
        ]
      },
      {
        "haneSayisi": 2,
        "tip": "SON_IKI_RAKAM",
        "ikramiye": 80,
        "numaralar": ["03", "75", "37", "92", "79", "05", "65", "20"]
      },
      {
        "haneSayisi": 1,
        "tip": "AMORTI",
        "ikramiye": 40,
        "numaralar": ["0", "7"]
      },
      {
        "haneSayisi": 0,
        "tip": "TESELLI",
        "ikramiye": 4000,
        "numaralar": [
          "481211",
          "431214",
          "431213",
          "531211",
          "438211",
          "331211",
          "431811",
          "731211",
          "401211",
          "431221",
          "931211",
          "436211",
          "431201",
          "461211",
          "431511",
          "831211",
          "431231",
          "231211",
          "441211",
          "431216",
          "431212",
          "431215",
          "431251",
          "432211",
          "433211",
          "431611",
          "431011",
          "431210",
          "421211",
          "430211",
          "435211",
          "491211",
          "131211",
          "631211",
          "437211",
          "431291",
          "431241",
          "439211",
          "431271",
          "471211",
          "431218",
          "431111",
          "431411",
          "031211",
          "431911",
          "431711",
          "431281",
          "434211",
          "431217",
          "431219",
          "451211",
          "431261",
          "431311",
          "411211"
        ]
      }
    ],
    "buyukIkrKazananIlIlceler": [
      {
        "il": "07",
        "ilView": "ANTALYA",
        "ilce": "00700",
        "ilceView": "MERKEZ"
      },
      {
        "il": "106",
        "ilView": "SAYISAL SİSTEM (ANKARA)",
        "ilce": "106",
        "ilceView": " "
      },
      {
        "il": "34",
        "ilView": "İSTANBUL",
        "ilce": "03400",
        "ilceView": "MERKEZ"
      },
      { "il": "99", "ilView": "KKTC", "ilce": "09999", "ilceView": "MERKEZ" }
    ],
    "cekilisTarihiOld": "20190119"
  }
}
