{"archived":true,"oid":"sayisal_archived_20030719","hafta":349,"cekilisTarihi":"19/07/2003","cekilisTuru":"SAYISAL_LOTO","rakamlar":"05#12#16#32#33#38","rakamlarNumaraSirasi":"05 - 12 - 16 - 32 - 33 - 38","bilenKisiler":[{"oid":"sayisal_20030719_results_3","kisiBasinaDusenIkramiye":1.2,"kisiSayisi":721889,"tur":"$3_BILEN"},{"oid":"sayisal_20030719_results_4","kisiBasinaDusenIkramiye":10.85,"kisiSayisi":43404,"tur":"$4_BILEN"},{"oid":"sayisal_20030719_results_5","kisiBasinaDusenIkramiye":1018.05,"kisiSayisi":876,"tur":"$5_BILEN"},{"oid":"sayisal_20030719_results_6","kisiBasinaDusenIkramiye":1587923.3,"kisiSayisi":1,"tur":"$6_BILEN"}],"devretti":false,"devirSayisi":null,"devirTutari":0,"buyukIkramiye":1587923.3,"buyukIkrKazananIlIlceler":null}