{
  "success": true,
  "data": {
    "archived": true,
    "oid": "sayisal_archived_20070804",
    "hafta": 560,
    "cekilisTarihi": "04/08/2007",
    "cekilisTuru": "SAYISAL_LOTO",
    "rakamlar": "19#23#25#29#31#33",
    "rakamlarNumaraSirasi": "19 - 23 - 25 - 29 - 31 - 33",
    "bilenKisiler": [
      {
        "oid": "sayisal_20070804_results_3",
        "kisiBasinaDusenIkramiye": 3.35,
        "kisiSayisi": 338177,
        "tur": "$3_BILEN"
      },
      {
        "oid": "sayisal_20070804_results_4",
        "kisiBasinaDusenIkramiye": 19.7,
        "kisiSayisi": 18973,
        "tur": "$4_BILEN"
      },
      {
        "oid": "sayisal_20070804_results_5",
        "kisiBasinaDusenIkramiye": 1450.15,
        "kisiSayisi": 446,
        "tur": "$5_BILEN"
      },
      {
        "oid": "sayisal_20070804_results_6",
        "kisiBasinaDusenIkramiye": 478544.55,
        "kisiSayisi": 3,
        "tur": "$6_BILEN"
      }
    ],
    "devretti": false,
    "devirSayisi": null,
    "devirTutari": 0,
    "buyukIkramiye": 1435633.65,
    "buyukIkrKazananIlIlceler": null
  }
}
