{"archived":true,"oid":"sayisal_archived_20130824","hafta":876,"cekilisTarihi":"24/08/2013","cekilisTuru":"SAYISAL_LOTO","rakamlar":"03#06#14#25#38#39","rakamlarNumaraSirasi":"03 - 06 - 14 - 25 - 38 - 39","bilenKisiler":[{"oid":"sayisal_20130824_results_3","kisiBasinaDusenIkramiye":5.45,"kisiSayisi":228473,"tur":"$3_BILEN"},{"oid":"sayisal_20130824_results_4","kisiBasinaDusenIkramiye":37,"kisiSayisi":12155,"tur":"$4_BILEN"},{"oid":"sayisal_20130824_results_5","kisiBasinaDusenIkramiye":2948.15,"kisiSayisi":200,"tur":"$5_BILEN"},{"oid":"sayisal_20130824_results_6","kisiBasinaDusenIkramiye":1400216.65,"kisiSayisi":1,"tur":"$6_BILEN"}],"devretti":false,"devirSayisi":null,"devirTutari":0,"buyukIkramiye":1400216.65,"buyukIkrKazananIlIlceler":null}